sirio/Test.py
sirio/__init__.py
sirio/bo_extractor.py
sirio/business_object.py
sirio/event.py
sirio/exceptions.py
sirio/service.py
sirio/sirio_ai.py
sirio/sirio_batch_ai.py
sirio/sirio_report.py
sirio/utility.py
tests/__init__.py
tests/test_sirio.py
sirio-0.1.55.dist-info/METADATA
sirio-0.1.55.dist-info/WHEEL
sirio-0.1.55.dist-info/top_level.txt
sirio-0.1.55.dist-info/RECORD
