Metadata-Version: 2.1
Name: sirio
Version: 0.1.55
Summary: Sirio
Home-page: https://github.com/pask-xx/sirio.git
Author: Pasquale Rombolà
Author-email: pasquale.rombola@cerved.com
License: BSD
Keywords: sirio,template,package
Classifier: Development Status :: 4 - Beta
Classifier: Environment :: Console
Classifier: Intended Audience :: Developers
Classifier: Natural Language :: English
Classifier: License :: OSI Approved :: BSD License
Classifier: Programming Language :: Python
Classifier: Programming Language :: Python :: 3
Classifier: Programming Language :: Python :: 3.10
Classifier: Programming Language :: Python :: 3.11
Classifier: Programming Language :: Python :: 3.12
Classifier: Programming Language :: Python :: Implementation :: CPython
Classifier: Programming Language :: Python :: Implementation :: PyPy
Classifier: Topic :: Software Development
Requires-Python: >=3.8
Requires-Dist: requests
